attrbench/__init__.py
attrbench/lib/__init__.py
attrbench/lib/attribution_writer.py
attrbench/lib/krippendorff_alpha.py
attrbench/lib/make_adv_patch.py
attrbench/lib/nd_array_tree.py
attrbench/lib/scene_overlay_dataset.py
attrbench/lib/segmentation.py
attrbench/lib/stat.py
attrbench/lib/train_epoch.py
attrbench/lib/util.py
attrbench/lib/masking/__init__.py
attrbench/lib/masking/blurring_masker.py
attrbench/lib/masking/constant_masker.py
attrbench/lib/masking/image_masker.py
attrbench/lib/masking/masker.py
attrbench/lib/masking/random_masker.py
attrbench/lib/masking/sample_average_masker.py
attrbench/lib/masking/tabular_masker.py
attrbench/metrics/__init__.py
attrbench/metrics/masker_metric.py
attrbench/metrics/metric.py
attrbench/metrics/data_dependent/__init__.py
attrbench/metrics/data_dependent/class_distinction.py
attrbench/metrics/data_dependent/input_dependence_rate.py
attrbench/metrics/data_dependent/input_independence_rate.py
attrbench/metrics/data_dependent/model_contrast_score.py
attrbench/metrics/deletion/__init__.py
attrbench/metrics/deletion/_concat_results.py
attrbench/metrics/deletion/_dataset.py
attrbench/metrics/deletion/_get_predictions.py
attrbench/metrics/deletion/deletion.py
attrbench/metrics/deletion/irof.py
attrbench/metrics/deletion/result.py
attrbench/metrics/impact_coverage/__init__.py
attrbench/metrics/impact_coverage/_apply_patches.py
attrbench/metrics/impact_coverage/_compute_coverage.py
attrbench/metrics/impact_coverage/impact_coverage.py
attrbench/metrics/impact_coverage/result.py
attrbench/metrics/impact_score/__init__.py
attrbench/metrics/impact_score/_dataset.py
attrbench/metrics/impact_score/impact_score.py
attrbench/metrics/impact_score/result.py
attrbench/metrics/infidelity/__init__.py
attrbench/metrics/infidelity/_compute_perturbations.py
attrbench/metrics/infidelity/infidelity.py
attrbench/metrics/infidelity/perturbation_generator.py
attrbench/metrics/infidelity/result.py
attrbench/metrics/max_sensitivity/__init__.py
attrbench-0.0.2.dist-info/LICENSE
attrbench-0.0.2.dist-info/METADATA
attrbench-0.0.2.dist-info/WHEEL
attrbench-0.0.2.dist-info/top_level.txt
attrbench-0.0.2.dist-info/RECORD
